sphinxcontrib/screenshot.py
sphinxcontrib_screenshot-0.2.2.dist-info/LICENSE
sphinxcontrib_screenshot-0.2.2.dist-info/METADATA
sphinxcontrib_screenshot-0.2.2.dist-info/WHEEL
sphinxcontrib_screenshot-0.2.2.dist-info/top_level.txt
sphinxcontrib_screenshot-0.2.2.dist-info/RECORD
